Metadata-Version: 2.1
Name: a2y-smartray
Version: 0.8.2
Summary: A module that wraps SmartRay 3D camera SDK.
Home-page: http://www.sorobust.com/a2y/smartray.html
Author: Yu Han
Author-email: hanjunyu@163.com
License: Private
Platform: Windows
Platform: Linux
Classifier: Development Status :: 4 - Beta
Classifier: Intended Audience :: Developers
Classifier: License :: Free For Educational Use
Classifier: Programming Language :: Python :: 3.5
Classifier: Operating System :: Microsoft :: Windows :: Windows 10
Classifier: Operating System :: POSIX :: Linux
